[{"id":"65","hider":"E006","seeker":"P005"}, {"id":"66","hider":"D1F2","seeker":"M0D7"}, {"id":"67","hider":"B030","seeker":"M0D7"}, {"id":"68","hider":"A30A","seeker":"M0D7"}, {"id":"69","hider":"S1D8","seeker":"M0D7"}, {"id":"70","hider":"S3D2","seeker":"M0D7"}, {"id":"71","hider":"C29A","seeker":"M0D7"}, {"id":"72","hider":"C08A","seeker":"M0D7"}, {"id":"73","hider":"N354","seeker":"M0D7"}, {"id":"74","hider":"T1D0","seeker":"M0D7"}, {"id":"75","hider":"A1DC","seeker":"M0D7"}, {"id":"76","hider":"R304","seeker":"M0D7"}, {"id":"77","hider":"W2FC","seeker":"M0D7"}, {"id":"78","hider":"A074","seeker":"M0D7"}, {"id":"79","hider":"S22A","seeker":"M0D7"}, {"id":"80","hider":"I3A8","seeker":"M0D7"}, {"id":"81","hider":"M2A2","seeker":"M0D7"}, {"id":"82","hider":"I3A8","seeker":"J405"}, {"id":"83","hider":"M2A2","seeker":"J405"}, {"id":"84","hider":"C08A","seeker":"J405"}, {"id":"85","hider":"M3A6","seeker":"J405"}, {"id":"86","hider":"M2B0","seeker":"J405"}, {"id":"87","hider":"S2AC","seeker":"J405"}, {"id":"88","hider":"D1F2","seeker":"J405"}, {"id":"89","hider":"H374","seeker":"W205"}, {"id":"90","hider":"D110","seeker":"W205"}, {"id":"91","hider":"P2D4","seeker":"W205"}, {"id":"92","hider":"S3D2","seeker":"W205"}, {"id":"93","hider":"P005","seeker":"W205"}, {"id":"94","hider":"I3A8","seeker":"W205"}, {"id":"95","hider":"E2E4","seeker":"W205"}, {"id":"96","hider":"L0C8","seeker":"W205"}, {"id":"97","hider":"H3D4","seeker":"W205"}, {"id":"98","hider":"S1D8","seeker":"A149"}, {"id":"99","hider":"A30A","seeker":"A149"}, {"id":"100","hider":"C08A","seeker":"A149"}, {"id":"101","hider":"W2FC","seeker":"A149"}, {"id":"102","hider":"R304","seeker":"A149"}, {"id":"103","hider":"A074","seeker":"A149"}, {"id":"104","hider":"D110","seeker":"A149"}, {"id":"105","hider":"H374","seeker":"A149"}, {"id":"106","hider":"S1D8","seeker":"S229"}, {"id":"107","hider":"A30A","seeker":"S229"}, {"id":"108","hider":"C08A","seeker":"S229"}, {"id":"109","hider":"W2FC","seeker":"S229"}, {"id":"110","hider":"R304","seeker":"S229"}, {"id":"111","hider":"A074","seeker":"S229"}, {"id":"112","hider":"D110","seeker":"S229"}, {"id":"113","hider":"H374","seeker":"S229"}, {"id":"114","hider":"A02A","seeker":"J405"}, {"id":"115","hider":"N354","seeker":"W34D"}, {"id":"116","hider":"B030","seeker":"W34D"}, {"id":"117","hider":"V410","seeker":"W34D"}, {"id":"118","hider":"M080","seeker":"W34D"}, {"id":"119","hider":"H262","seeker":"W34D"}, {"id":"120","hider":"S268","seeker":"W34D"}, {"id":"121","hider":"M3C0","seeker":"W205"}, {"id":"122","hider":"M2A2","seeker":"B3DB"}, {"id":"123","hider":"C08A","seeker":"B3DB"}, {"id":"124","hider":"N354","seeker":"B3DB"}, {"id":"125","hider":"B030","seeker":"B3DB"}, {"id":"126","hider":"C204","seeker":"W205"}, {"id":"127","hider":"S406","seeker":"I335"}, {"id":"128","hider":"F106","seeker":"I335"}, {"id":"129","hider":"D110","seeker":"F1D1"}, {"id":"130","hider":"H374","seeker":"F1D1"}, {"id":"131","hider":"S22A","seeker":"F1D1"}, {"id":"132","hider":"C29A","seeker":"J393"}, {"id":"133","hider":"M2A2","seeker":"J393"}, {"id":"134","hider":"V410","seeker":"J393"}, {"id":"135","hider":"C08A","seeker":"J393"}, {"id":"136","hider":"S22A","seeker":"J393"}, {"id":"137","hider":"M3C0","seeker":"J393"}, {"id":"138","hider":"M080","seeker":"J393"}, {"id":"139","hider":"A048","seeker":"J393"}, {"id":"140","hider":"B030","seeker":"J393"}, {"id":"141","hider":"A376","seeker":"J393"}, {"id":"142","hider":"S3D2","seeker":"J393"}, {"id":"143","hider":"T32D","seeker":"S22A"}, {"id":"144","hider":"M0D7","seeker":"S22A"}, {"id":"145","hider":"A191","seeker":"S22A"}, {"id":"146","hider":"D3B5","seeker":"S22A"}, {"id":"147","hider":"D2D7","seeker":"S22A"}, {"id":"148","hider":"N2BB","seeker":"S22A"}, {"id":"149","hider":"S183","seeker":"S22A"}, {"id":"150","hider":"E2E1","seeker":"K0E2"}, {"id":"151","hider":"G0BE","seeker":"C0E1"}, {"id":"152","hider":"I3A8","seeker":"C0E1"}, {"id":"153","hider":"M2A2","seeker":"C0E1"}, {"id":"154","hider":"C08A","seeker":"C0E1"}, {"id":"155","hider":"M3A6","seeker":"C0E1"}, {"id":"156","hider":"S2AC","seeker":"C0E1"}, {"id":"157","hider":"M2D6","seeker":"C0E1"}, {"id":"158","hider":"R25C","seeker":"C0E1"}, {"id":"159","hider":"K3C8","seeker":"C0E1"}, {"id":"160","hider":"A376","seeker":"Z1C3"}, {"id":"161","hider":"I3A8","seeker":"Z1C3"}, {"id":"162","hider":"S22A","seeker":"Z1C3"}, {"id":"163","hider":"M2A2","seeker":"Z1C3"}, {"id":"164","hider":"B030","seeker":"Z1C3"}, {"id":"165","hider":"M3A6","seeker":"Z1C3"}, {"id":"166","hider":"S3D2","seeker":"Z1C3"}, {"id":"167","hider":"C27C","seeker":"F1D1"}, {"id":"168","hider":"I3A8","seeker":"F1D1"}, {"id":"169","hider":"M2A2","seeker":"F1D1"}, {"id":"170","hider":"W2FC","seeker":"F1D1"}, {"id":"171","hider":"A30A","seeker":"F1D1"}, {"id":"172","hider":"R069","seeker":"M2B0"}, {"id":"173","hider":"P403","seeker":"M2B0"}, {"id":"174","hider":"X3B7","seeker":"M2B0"}, {"id":"175","hider":"K3B1","seeker":"M2B0"}, {"id":"176","hider":"I02B","seeker":"M2B0"}, {"id":"177","hider":"C3C6","seeker":"C0E1"}, {"id":"178","hider":"R3CA","seeker":"C0E1"}, {"id":"179","hider":"S3E2","seeker":"C0E1"}, {"id":"180","hider":"M3C0","seeker":"C0E1"}, {"id":"181","hider":"P2D4","seeker":"M10B"}, {"id":"182","hider":"D110","seeker":"M10B"}, {"id":"183","hider":"S22A","seeker":"M10B"}, {"id":"184","hider":"C27C","seeker":"M10B"}, {"id":"185","hider":"R069","seeker":"B030"}, {"id":"186","hider":"D3B5","seeker":"B030"}, {"id":"187","hider":"N2BB","seeker":"B030"}, {"id":"188","hider":"D2D7","seeker":"B030"}, {"id":"189","hider":"L2BC","seeker":"B030"}, {"id":"190","hider":"J405","seeker":"B030"}, {"id":"191","hider":"R185","seeker":"C3C6"}, {"id":"192","hider":"J263","seeker":"C3C6"}, {"id":"193","hider":"R069","seeker":"C3C6"}, {"id":"194","hider":"H1CF","seeker":"C3C6"}, {"id":"195","hider":"C1CB","seeker":"C3C6"}, {"id":"196","hider":"E3F5","seeker":"C3C6"}, {"id":"197","hider":"A191","seeker":"C3C6"}, {"id":"198","hider":"D363","seeker":"C3C6"}, {"id":"199","hider":"M415","seeker":"C3C6"}, {"id":"200","hider":"A074","seeker":"F1D1"}, {"id":"201","hider":"R069","seeker":"S2AC"}, {"id":"202","hider":"P403","seeker":"S2AC"}, {"id":"203","hider":"X3B7","seeker":"S2AC"}, {"id":"204","hider":"K3B1","seeker":"S2AC"}, {"id":"205","hider":"C22D","seeker":"S2AC"}, {"id":"206","hider":"T0AF","seeker":"S2AC"}, {"id":"207","hider":"E321","seeker":"S2AC"}, {"id":"208","hider":"F3D7","seeker":"S2AC"}, {"id":"209","hider":"M10B","seeker":"S2AC"}, {"id":"210","hider":"C23A","seeker":"R223"}, {"id":"211","hider":"A048","seeker":"E321"}, {"id":"212","hider":"V410","seeker":"E321"}, {"id":"213","hider":"M3C0","seeker":"E321"}, {"id":"214","hider":"M2A2","seeker":"E321"}, {"id":"215","hider":"W2FC","seeker":"E321"}, {"id":"216","hider":"A074","seeker":"E321"}, {"id":"217","hider":"C08A","seeker":"E321"}, {"id":"218","hider":"D110","seeker":"E321"}, {"id":"219","hider":"H374","seeker":"E321"}, {"id":"220","hider":"P403","seeker":"A376"}, {"id":"221","hider":"X3B7","seeker":"A376"}, {"id":"222","hider":"A191","seeker":"A376"}, {"id":"223","hider":"E2E1","seeker":"A376"}, {"id":"224","hider":"R069","seeker":"A376"}, {"id":"225","hider":"A3A5","seeker":"A376"}, {"id":"226","hider":"P3A7","seeker":"A376"}, {"id":"227","hider":"R185","seeker":"S3E2"}, {"id":"228","hider":"J263","seeker":"S3E2"}, {"id":"229","hider":"R069","seeker":"S3E2"}, {"id":"230","hider":"H1CF","seeker":"S3E2"}, {"id":"231","hider":"C1CB","seeker":"S3E2"}, {"id":"232","hider":"E3F5","seeker":"S3E2"}, {"id":"233","hider":"A191","seeker":"S3E2"}, {"id":"234","hider":"D363","seeker":"S3E2"}, {"id":"235","hider":"P2D4","seeker":"C22D"}, {"id":"236","hider":"D110","seeker":"C22D"}, {"id":"237","hider":"H374","seeker":"C22D"}, {"id":"238","hider":"S22A","seeker":"C22D"}, {"id":"239","hider":"C27C","seeker":"C22D"}, {"id":"240","hider":"I3A8","seeker":"C22D"}, {"id":"241","hider":"M2A2","seeker":"C22D"}, {"id":"242","hider":"W2FC","seeker":"C22D"}, {"id":"243","hider":"A30A","seeker":"C22D"}, {"id":"244","hider":"T233","seeker":"J1AC"}, {"id":"245","hider":"T401","seeker":"K10A"}, {"id":"246","hider":"M20F","seeker":"K10A"}, {"id":"247","hider":"R223","seeker":"K10A"}, {"id":"248","hider":"M35F","seeker":"K10A"}, {"id":"249","hider":"W205","seeker":"K10A"}, {"id":"250","hider":"M415","seeker":"K10A"}, {"id":"251","hider":"M3C1","seeker":"T11C"}, {"id":"252","hider":"T32D","seeker":"T11C"}, {"id":"253","hider":"J263","seeker":"T11C"}, {"id":"254","hider":"J341","seeker":"T11C"}, {"id":"255","hider":"K107","seeker":"T11C"}, {"id":"256","hider":"J0E5","seeker":"T11C"}, {"id":"257","hider":"Z1C3","seeker":"H2A8"}, {"id":"258","hider":"A193","seeker":"H2A8"}, {"id":"259","hider":"W195","seeker":"H2A8"}, {"id":"260","hider":"W08F","seeker":"H2A8"}, {"id":"261","hider":"E0F9","seeker":"H2A8"}, {"id":"262","hider":"R185","seeker":"H2A8"}, {"id":"263","hider":"J263","seeker":"H2A8"}, {"id":"264","hider":"R069","seeker":"H2A8"}, {"id":"265","hider":"E2E1","seeker":"H2A8"}, {"id":"266","hider":"D2D7","seeker":"H2A8"}, {"id":"267","hider":"N2BB","seeker":"H2A8"}, {"id":"268","hider":"D3B5","seeker":"H2A8"}, {"id":"269","hider":"R069","seeker":"V3CE"}, {"id":"270","hider":"J263","seeker":"V3CE"}, {"id":"271","hider":"R185","seeker":"V3CE"}, {"id":"272","hider":"J405","seeker":"V3CE"}, {"id":"273","hider":"R223","seeker":"V3CE"}, {"id":"274","hider":"M415","seeker":"V3CE"}, {"id":"275","hider":"S183","seeker":"M3A6"}, {"id":"276","hider":"C21B","seeker":"M3A6"}, {"id":"277","hider":"P403","seeker":"M3A6"}, {"id":"278","hider":"X3B7","seeker":"M3A6"}, {"id":"279","hider":"E2E1","seeker":"M3A6"}, {"id":"280","hider":"L2BC","seeker":"M3A6"}, {"id":"281","hider":"N2BB","seeker":"M3A6"}, {"id":"282","hider":"D3B5","seeker":"M3A6"}, {"id":"283","hider":"T32D","seeker":"M3A6"}, {"id":"284","hider":"W195","seeker":"E286"}, {"id":"285","hider":"Z1C3","seeker":"E286"}, {"id":"286","hider":"A193","seeker":"E286"}, {"id":"287","hider":"M0E3","seeker":"E286"}, {"id":"288","hider":"J0E5","seeker":"S27E"}, {"id":"289","hider":"C21B","seeker":"S27E"}, {"id":"290","hider":"T32D","seeker":"A30A"}, {"id":"291","hider":"M0D7","seeker":"A30A"}, {"id":"292","hider":"R069","seeker":"A30A"}, {"id":"293","hider":"D2D7","seeker":"A30A"}, {"id":"294","hider":"N2BB","seeker":"A30A"}, {"id":"295","hider":"L2BC","seeker":"A30A"}, {"id":"296","hider":"D3B5","seeker":"A30A"}, {"id":"297","hider":"E2E1","seeker":"A30A"}, {"id":"298","hider":"C0E1","seeker":"J13A"}, {"id":"299","hider":"T401","seeker":"J13A"}, {"id":"300","hider":"M20F","seeker":"J13A"}, {"id":"301","hider":"J0E5","seeker":"V276"}, {"id":"302","hider":"C21B","seeker":"V276"}, {"id":"303","hider":"P403","seeker":"R25C"}, {"id":"304","hider":"X3B7","seeker":"R25C"}, {"id":"305","hider":"E2E1","seeker":"R25C"}, {"id":"306","hider":"M145","seeker":"R25C"}, {"id":"307","hider":"L2BC","seeker":"R25C"}, {"id":"308","hider":"N2BB","seeker":"R25C"}, {"id":"309","hider":"J263","seeker":"R25C"}, {"id":"310","hider":"R185","seeker":"R25C"}, {"id":"311","hider":"T32D","seeker":"C29A"}, {"id":"312","hider":"R069","seeker":"C29A"}, {"id":"313","hider":"N2BB","seeker":"C29A"}, {"id":"314","hider":"R185","seeker":"C29A"}, {"id":"315","hider":"J263","seeker":"C29A"}, {"id":"316","hider":"J27F","seeker":"J280"}, {"id":"317","hider":"W195","seeker":"J280"}, {"id":"318","hider":"Z1C3","seeker":"J280"}, {"id":"319","hider":"A193","seeker":"J280"}, {"id":"320","hider":"M0E3","seeker":"J280"}, {"id":"321","hider":"W08F","seeker":"J280"}, {"id":"322","hider":"E0F9","seeker":"J280"}, {"id":"323","hider":"K3B1","seeker":"J280"}, {"id":"324","hider":"I02B","seeker":"J280"}, {"id":"325","hider":"F3D7","seeker":"J280"}, {"id":"326","hider":"K107","seeker":"J280"}, {"id":"327","hider":"J341","seeker":"J280"}, {"id":"328","hider":"A2C5","seeker":"J280"}, {"id":"329","hider":"Z1AB","seeker":"J280"}, {"id":"330","hider":"W343","seeker":"J280"}, {"id":"331","hider":"J0E5","seeker":"J280"}, {"id":"332","hider":"C21B","seeker":"J280"}, {"id":"333","hider":"P403","seeker":"T1D0"}, {"id":"334","hider":"E2E1","seeker":"T1D0"}, {"id":"335","hider":"X3B7","seeker":"T1D0"}, {"id":"336","hider":"S183","seeker":"T1D0"}, {"id":"337","hider":"G0F2","seeker":"H1CF"}, {"id":"338","hider":"P005","seeker":"H1CF"}, {"id":"339","hider":"S1D8","seeker":"H1CF"}, {"id":"340","hider":"D1F2","seeker":"H1CF"}, {"id":"341","hider":"C29A","seeker":"H1CF"}, {"id":"342","hider":"A30A","seeker":"H1CF"}, {"id":"343","hider":"N354","seeker":"H1CF"}, {"id":"344","hider":"W2FC","seeker":"H1CF"}, {"id":"345","hider":"A074","seeker":"H1CF"}, {"id":"346","hider":"R304","seeker":"H1CF"}, {"id":"347","hider":"C08A","seeker":"H1CF"}, {"id":"348","hider":"M2A2","seeker":"H1CF"}, {"id":"349","hider":"S2AC","seeker":"H1CF"}, {"id":"350","hider":"M2B0","seeker":"H1CF"}, {"id":"351","hider":"M3A6","seeker":"H1CF"}, {"id":"352","hider":"S22A","seeker":"H1CF"}, {"id":"353","hider":"E2E4","seeker":"H1CF"}, {"id":"354","hider":"P3B2","seeker":"M145"}, {"id":"355","hider":"W2FC","seeker":"M145"}, {"id":"356","hider":"S122","seeker":"M145"}, {"id":"357","hider":"A124","seeker":"M145"}, {"id":"358","hider":"A1E6","seeker":"M145"}, {"id":"359","hider":"S22A","seeker":"M145"}, {"id":"360","hider":"R304","seeker":"M145"}, {"id":"361","hider":"P3D0","seeker":"M145"}, {"id":"362","hider":"B030","seeker":"M145"}, {"id":"363","hider":"P2D4","seeker":"M145"}, {"id":"364","hider":"S303","seeker":"J210"}, {"id":"365","hider":"R069","seeker":"J210"}, {"id":"366","hider":"A2D5","seeker":"P2D4"}, {"id":"367","hider":"C0E1","seeker":"P2D4"}, {"id":"368","hider":"M031","seeker":"P2D4"}, {"id":"369","hider":"N2C3","seeker":"P2D4"}, {"id":"370","hider":"J263","seeker":"P2D4"}, {"id":"371","hider":"A047","seeker":"T233"}, {"id":"372","hider":"B030","seeker":"T233"}, {"id":"373","hider":"P005","seeker":"T233"}, {"id":"374","hider":"G0BE","seeker":"T233"}, {"id":"375","hider":"B21E","seeker":"T233"}, {"id":"376","hider":"P04B","seeker":"V416"}, {"id":"377","hider":"T3DF","seeker":"V416"}, {"id":"378","hider":"M349","seeker":"V416"}, {"id":"379","hider":"R34B","seeker":"V416"}, {"id":"380","hider":"J1D9","seeker":"V416"}, {"id":"381","hider":"F1DB","seeker":"V416"}, {"id":"382","hider":"K41F","seeker":"V416"}, {"id":"383","hider":"B3DB","seeker":"V416"}, {"id":"384","hider":"W34D","seeker":"V416"}, {"id":"385","hider":"C1CD","seeker":"V416"}, {"id":"386","hider":"G331","seeker":"V416"}, {"id":"387","hider":"A32A","seeker":"V416"}, {"id":"388","hider":"N2C3","seeker":"V416"}, {"id":"389","hider":"M031","seeker":"V416"}, {"id":"390","hider":"M0D7","seeker":"D110"}, {"id":"391","hider":"R069","seeker":"D110"}, {"id":"392","hider":"S183","seeker":"D110"}, {"id":"393","hider":"D2D7","seeker":"D110"}, {"id":"394","hider":"N2BB","seeker":"D110"}, {"id":"395","hider":"L2BC","seeker":"D110"}, {"id":"396","hider":"R185","seeker":"D110"}, {"id":"397","hider":"J263","seeker":"D110"}, {"id":"398","hider":"M3C1","seeker":"D110"}, {"id":"399","hider":"M0D7","seeker":"H374"}, {"id":"400","hider":"R069","seeker":"H374"}, {"id":"401","hider":"S183","seeker":"H374"}, {"id":"402","hider":"D2D7","seeker":"H374"}, {"id":"403","hider":"L2BC","seeker":"H374"}, {"id":"404","hider":"R185","seeker":"H374"}, {"id":"405","hider":"J263","seeker":"H374"}, {"id":"406","hider":"M3C1","seeker":"H374"}, {"id":"407","hider":"B402","seeker":"C1CD"}, {"id":"408","hider":"J210","seeker":"C1CD"}, {"id":"409","hider":"M3A6","seeker":"M145"}, {"id":"410","hider":"S2AC","seeker":"M145"}, {"id":"411","hider":"M2B0","seeker":"M145"}, {"id":"412","hider":"P04B","seeker":"P3E4"}, {"id":"413","hider":"T3DF","seeker":"P3E4"}, {"id":"414","hider":"M349","seeker":"P3E4"}, {"id":"415","hider":"R34B","seeker":"P3E4"}, {"id":"416","hider":"J1D9","seeker":"P3E4"}, {"id":"417","hider":"F1DB","seeker":"P3E4"}, {"id":"418","hider":"K41F","seeker":"P3E4"}, {"id":"419","hider":"B3DB","seeker":"P3E4"}, {"id":"420","hider":"W34D","seeker":"P3E4"}, {"id":"421","hider":"G331","seeker":"P3E4"}, {"id":"422","hider":"M2B0","seeker":"C0E1"}, {"id":"423","hider":"E2E1","seeker":"T230"}, {"id":"424","hider":"M0D7","seeker":"T230"}, {"id":"425","hider":"R185","seeker":"T230"}, {"id":"426","hider":"J263","seeker":"T230"}, {"id":"427","hider":"F3D7","seeker":"T230"}, {"id":"428","hider":"W343","seeker":"T230"}, {"id":"429","hider":"A2C5","seeker":"T230"}, {"id":"430","hider":"L40D","seeker":"T230"}, {"id":"431","hider":"A30A","seeker":"A313"}, {"id":"432","hider":"P2D4","seeker":"A313"}, {"id":"433","hider":"B030","seeker":"A313"}, {"id":"434","hider":"A2C4","seeker":"A313"}, {"id":"435","hider":"M31C","seeker":"A313"}, {"id":"436","hider":"P2BF","seeker":"A313"}, {"id":"437","hider":"M2CA","seeker":"A313"}, {"id":"438","hider":"K346","seeker":"A313"}, {"id":"439","hider":"S3DC","seeker":"A313"}, {"id":"440","hider":"I3A8","seeker":"A313"}, {"id":"441","hider":"M2A2","seeker":"A313"}, {"id":"442","hider":"C08A","seeker":"A313"}, {"id":"443","hider":"A074","seeker":"A313"}, {"id":"444","hider":"W2FC","seeker":"A313"}, {"id":"445","hider":"M2B0","seeker":"A313"}, {"id":"446","hider":"P3B2","seeker":"A313"}, {"id":"447","hider":"J220","seeker":"A313"}, {"id":"448","hider":"A2C4","seeker":"R10F"}, {"id":"449","hider":"M31C","seeker":"R10F"}, {"id":"450","hider":"K346","seeker":"R10F"}, {"id":"451","hider":"M2CA","seeker":"R10F"}, {"id":"452","hider":"S3DC","seeker":"R10F"}, {"id":"453","hider":"I3A8","seeker":"R10F"}, {"id":"454","hider":"M2A2","seeker":"R10F"}, {"id":"455","hider":"B21E","seeker":"R10F"}, {"id":"456","hider":"J220","seeker":"R10F"}, {"id":"457","hider":"M3A6","seeker":"R10F"}, {"id":"458","hider":"S2AC","seeker":"R10F"}, {"id":"459","hider":"M2B0","seeker":"R10F"}, {"id":"460","hider":"P3B2","seeker":"R10F"}, {"id":"461","hider":"A04F","seeker":"A02A"}, {"id":"462","hider":"M24F","seeker":"A02A"}, {"id":"463","hider":"C21B","seeker":"A02A"}, {"id":"464","hider":"C08A","seeker":"A2FD"}, {"id":"465","hider":"S22A","seeker":"A2FD"}, {"id":"466","hider":"P005","seeker":"A2FD"}, {"id":"467","hider":"I3A8","seeker":"A2FD"}, {"id":"468","hider":"M2A2","seeker":"A2FD"}, {"id":"469","hider":"D110","seeker":"A2FD"}, {"id":"470","hider":"H374","seeker":"A2FD"}, {"id":"471","hider":"N2FF","seeker":"A2FD"}, {"id":"472","hider":"S309","seeker":"A2FD"}, {"id":"473","hider":"M2FE","seeker":"A2FD"}, {"id":"474","hider":"C27C","seeker":"M145"}, {"id":"475","hider":"A2C4","seeker":"M315"}, {"id":"476","hider":"M31C","seeker":"M315"}, {"id":"477","hider":"P2BF","seeker":"M315"}, {"id":"478","hider":"K346","seeker":"M315"}, {"id":"479","hider":"M2CA","seeker":"M315"}, {"id":"480","hider":"J220","seeker":"M315"}, {"id":"481","hider":"A074","seeker":"M315"}, {"id":"482","hider":"B030","seeker":"M315"}, {"id":"483","hider":"S3DC","seeker":"E0E9"}, {"id":"484","hider":"K346","seeker":"E0E9"}, {"id":"485","hider":"A048","seeker":"E0E9"}, {"id":"486","hider":"M2A2","seeker":"E0E9"}, {"id":"487","hider":"M3A6","seeker":"E0E9"}, {"id":"488","hider":"S2AC","seeker":"E0E9"}, {"id":"489","hider":"M2B0","seeker":"E0E9"}, {"id":"490","hider":"P3B2","seeker":"E0E9"}, {"id":"491","hider":"M31C","seeker":"E0E9"}, {"id":"492","hider":"P2BF","seeker":"E0E9"}, {"id":"493","hider":"M2CA","seeker":"E0E9"}, {"id":"494","hider":"B21E","seeker":"E0E9"}, {"id":"495","hider":"I3A8","seeker":"E0E9"}, {"id":"496","hider":"I3A8","seeker":"A1D7"}, {"id":"497","hider":"M3A6","seeker":"A1D7"}, {"id":"498","hider":"C08A","seeker":"A1D7"}, {"id":"499","hider":"B21E","seeker":"A1D7"}, {"id":"500","hider":"J220","seeker":"A1D7"}, {"id":"501","hider":"B030","seeker":"A1D7"}, {"id":"502","hider":"P2D4","seeker":"A1D7"}, {"id":"503","hider":"H374","seeker":"A1D7"}, {"id":"504","hider":"D110","seeker":"A1D7"}, {"id":"505","hider":"A376","seeker":"A1D7"}, {"id":"506","hider":"G0BE","seeker":"A1D7"}, {"id":"507","hider":"P005","seeker":"A1D7"}, {"id":"508","hider":"S3DC","seeker":"G3AF"}, {"id":"509","hider":"K346","seeker":"G3AF"}, {"id":"510","hider":"A048","seeker":"G3AF"}, {"id":"511","hider":"I3A8","seeker":"G3AF"}, {"id":"512","hider":"M2A2","seeker":"G3AF"}, {"id":"513","hider":"B21E","seeker":"G3AF"}, {"id":"514","hider":"J220","seeker":"G3AF"}, {"id":"515","hider":"M3A6","seeker":"G3AF"}, {"id":"516","hider":"S2AC","seeker":"G3AF"}, {"id":"517","hider":"P3B2","seeker":"G3AF"}, {"id":"518","hider":"H2A8","seeker":"E3F5"}, {"id":"519","hider":"K0E2","seeker":"E3F5"}, {"id":"520","hider":"M332","seeker":"E3F5"}, {"id":"521","hider":"S2F4","seeker":"E3F5"}, {"id":"522","hider":"M2A2","seeker":"E3F5"}, {"id":"523","hider":"C08A","seeker":"E3F5"}, {"id":"524","hider":"R304","seeker":"E3F5"}, {"id":"525","hider":"W2FC","seeker":"E3F5"}, {"id":"526","hider":"F32E","seeker":"E3F5"}, {"id":"527","hider":"A074","seeker":"E3F5"}, {"id":"528","hider":"N354","seeker":"E3F5"}, {"id":"529","hider":"A30A","seeker":"E3F5"}, {"id":"530","hider":"B030","seeker":"E3F5"}, {"id":"531","hider":"T0AF","seeker":"W29E"}, {"id":"532","hider":"E321","seeker":"W29E"}, {"id":"533","hider":"L40D","seeker":"W29E"}, {"id":"534","hider":"A3A5","seeker":"W29E"}, {"id":"535","hider":"P3A7","seeker":"W29E"}, {"id":"536","hider":"E321","seeker":"A2A0"}, {"id":"537","hider":"L40D","seeker":"A2A0"}, {"id":"538","hider":"M349","seeker":"V260"}, {"id":"539","hider":"R34B","seeker":"V260"}, {"id":"540","hider":"J1D9","seeker":"V260"}, {"id":"541","hider":"F1DB","seeker":"V260"}, {"id":"542","hider":"K41F","seeker":"V260"}, {"id":"543","hider":"C0E1","seeker":"V260"}, {"id":"544","hider":"M35F","seeker":"V260"}, {"id":"545","hider":"S29B","seeker":"V260"}, {"id":"546","hider":"W2DF","seeker":"V260"}, {"id":"547","hider":"M031","seeker":"V260"}, {"id":"548","hider":"T0AF","seeker":"A2A0"}, {"id":"549","hider":"P3A7","seeker":"A2A0"}, {"id":"550","hider":"W2FC","seeker":"E2D9"}, {"id":"551","hider":"R304","seeker":"E2D9"}, {"id":"552","hider":"M256","seeker":"E2D9"}, {"id":"553","hider":"V255","seeker":"E2D9"}, {"id":"554","hider":"N354","seeker":"E2D9"}, {"id":"555","hider":"A30A","seeker":"E2D9"}, {"id":"556","hider":"H374","seeker":"E2D9"}, {"id":"557","hider":"D110","seeker":"E2D9"}, {"id":"558","hider":"B030","seeker":"E2D9"}, {"id":"559","hider":"G3FC","seeker":"E3A4"}, {"id":"560","hider":"R1A7","seeker":"E3A4"}, {"id":"561","hider":"J13B","seeker":"S3DC"}, {"id":"562","hider":"V09B","seeker":"S3DC"}, {"id":"563","hider":"Z1AB","seeker":"S3DC"}, {"id":"564","hider":"A2C5","seeker":"S3DC"}, {"id":"565","hider":"W343","seeker":"S3DC"}, {"id":"566","hider":"E321","seeker":"R1E0"}, {"id":"567","hider":"T0AF","seeker":"R1E0"}, {"id":"568","hider":"I335","seeker":"R1E0"}, {"id":"569","hider":"F1D1","seeker":"R1E0"}, {"id":"570","hider":"C22D","seeker":"R1E0"}, {"id":"571","hider":"V416","seeker":"S21D"}, {"id":"572","hider":"P3E4","seeker":"S21D"}, {"id":"573","hider":"W29E","seeker":"S21D"}, {"id":"574","hider":"C23A","seeker":"S21D"}, {"id":"575","hider":"H2A8","seeker":"H2DB"}, {"id":"576","hider":"S2F4","seeker":"H2DB"}, {"id":"577","hider":"I3A8","seeker":"H2DB"}, {"id":"578","hider":"M2A2","seeker":"H2DB"}, {"id":"579","hider":"N354","seeker":"H2DB"}, {"id":"580","hider":"M332","seeker":"H2DB"}, {"id":"581","hider":"B030","seeker":"H2DB"}, {"id":"582","hider":"R304","seeker":"H2DB"}, {"id":"583","hider":"A074","seeker":"H2DB"}, {"id":"584","hider":"M306","seeker":"A2FD"}, {"id":"585","hider":"T32D","seeker":"G0F2"}, {"id":"586","hider":"S268","seeker":"P04B"}, {"id":"587","hider":"H262","seeker":"P04B"}, {"id":"588","hider":"T11C","seeker":"P04B"}, {"id":"589","hider":"K10A","seeker":"P04B"}, {"id":"590","hider":"K412","seeker":"P04B"}, {"id":"591","hider":"M12A","seeker":"P04B"}, {"id":"592","hider":"V260","seeker":"P04B"}, {"id":"593","hider":"M348","seeker":"P04B"}, {"id":"594","hider":"S24A","seeker":"P04B"}, {"id":"595","hider":"M415","seeker":"G0F2"}, {"id":"596","hider":"R185","seeker":"G0F2"}, {"id":"597","hider":"J263","seeker":"G0F2"}, {"id":"598","hider":"M0D7","seeker":"G0F2"}, {"id":"599","hider":"M0D7","seeker":"S2F4"}, {"id":"600","hider":"J263","seeker":"S2F4"}, {"id":"601","hider":"A2C5","seeker":"S2F4"}, {"id":"602","hider":"W343","seeker":"S2F4"}, {"id":"603","hider":"Z1AB","seeker":"S2F4"}, {"id":"604","hider":"J1D9","seeker":"S2F4"}, {"id":"605","hider":"K41F","seeker":"S2F4"}, {"id":"606","hider":"F1DB","seeker":"S2F4"}, {"id":"607","hider":"D3CB","seeker":"S2F4"}, {"id":"608","hider":"F21F","seeker":"S2F4"}, {"id":"609","hider":"X3B7","seeker":"J220"}, {"id":"610","hider":"R069","seeker":"J220"}, {"id":"611","hider":"J341","seeker":"J220"}, {"id":"612","hider":"K107","seeker":"J220"}, {"id":"613","hider":"R185","seeker":"J220"}, {"id":"614","hider":"J263","seeker":"J220"}, {"id":"615","hider":"M0D7","seeker":"J220"}, {"id":"616","hider":"R185","seeker":"S2F4"}, {"id":"617","hider":"A1D7","seeker":"S2F4"}, {"id":"618","hider":"P403","seeker":"J220"}, {"id":"619","hider":"A193","seeker":"E2E4"}, {"id":"620","hider":"Z1C3","seeker":"E2E4"}, {"id":"621","hider":"W195","seeker":"E2E4"}, {"id":"622","hider":"M0E3","seeker":"E2E4"}, {"id":"623","hider":"W08F","seeker":"E2E4"}, {"id":"624","hider":"E3F5","seeker":"E2E4"}, {"id":"625","hider":"S3A3","seeker":"E2E4"}, {"id":"626","hider":"N28B","seeker":"E2E4"}, {"id":"627","hider":"P403","seeker":"E2E4"}, {"id":"628","hider":"X3B7","seeker":"E2E4"}, {"id":"629","hider":"M367","seeker":"E2E4"}, {"id":"630","hider":"M3C1","seeker":"L0C8"}, {"id":"631","hider":"T32D","seeker":"L0C8"}, {"id":"632","hider":"P403","seeker":"L0C8"}, {"id":"633","hider":"X3B7","seeker":"L0C8"}, {"id":"634","hider":"E2E1","seeker":"L0C8"}, {"id":"635","hider":"R069","seeker":"L0C8"}, {"id":"636","hider":"N2BB","seeker":"L0C8"}, {"id":"637","hider":"L2BC","seeker":"L0C8"}, {"id":"638","hider":"D3B5","seeker":"L0C8"}, {"id":"639","hider":"J263","seeker":"L0C8"}, {"id":"640","hider":"R185","seeker":"L0C8"}, {"id":"641","hider":"S183","seeker":"B21E"}, {"id":"642","hider":"X3B7","seeker":"B21E"}, {"id":"643","hider":"J341","seeker":"B21E"}, {"id":"644","hider":"K107","seeker":"B21E"}, {"id":"645","hider":"R185","seeker":"B21E"}, {"id":"646","hider":"J263","seeker":"B21E"}, {"id":"647","hider":"G331","seeker":"S2F4"}, {"id":"648","hider":"C1CD","seeker":"S2F4"}, {"id":"649","hider":"R223","seeker":"S2F4"}, {"id":"650","hider":"M0D7","seeker":"Z2DC"}, {"id":"651","hider":"C21B","seeker":"Z2DC"}, {"id":"652","hider":"M0D7","seeker":"C2DA"}, {"id":"653","hider":"C21B","seeker":"C2DA"}, {"id":"654","hider":"R10F","seeker":"A21A"}, {"id":"655","hider":"M315","seeker":"A21A"}, {"id":"656","hider":"A313","seeker":"A21A"}, {"id":"657","hider":"T401","seeker":"A21A"}, {"id":"658","hider":"M20F","seeker":"A21A"}, {"id":"659","hider":"A2D5","seeker":"A21A"}, {"id":"660","hider":"C3EB","seeker":"A21A"}, {"id":"661","hider":"A3E7","seeker":"A21A"}, {"id":"662","hider":"J24C","seeker":"A21A"}, {"id":"663","hider":"Z18D","seeker":"A21A"}, {"id":"664","hider":"D261","seeker":"A21A"}, {"id":"665","hider":"C0E1","seeker":"A21A"}, {"id":"666","hider":"O1BB","seeker":"A21A"}, {"id":"667","hider":"A193","seeker":"A124"}, {"id":"668","hider":"Z1C3","seeker":"A124"}, {"id":"669","hider":"W195","seeker":"A124"}, {"id":"670","hider":"M031","seeker":"A124"}, {"id":"671","hider":"J341","seeker":"A124"}, {"id":"672","hider":"K107","seeker":"A124"}, {"id":"673","hider":"M145","seeker":"A124"}, {"id":"674","hider":"R185","seeker":"A124"}, {"id":"675","hider":"J263","seeker":"A124"}, {"id":"676","hider":"R069","seeker":"A124"}, {"id":"677","hider":"A193","seeker":"S122"}, {"id":"678","hider":"Z1C3","seeker":"S122"}, {"id":"679","hider":"W195","seeker":"S122"}, {"id":"680","hider":"M0E3","seeker":"S122"}, {"id":"681","hider":"W08F","seeker":"S122"}, {"id":"682","hider":"E0F9","seeker":"S122"}, {"id":"683","hider":"M0D7","seeker":"S122"}, {"id":"684","hider":"M031","seeker":"S122"}, {"id":"685","hider":"N2C3","seeker":"S122"}, {"id":"686","hider":"M3C1","seeker":"S122"}, {"id":"687","hider":"J341","seeker":"S122"}, {"id":"688","hider":"K107","seeker":"S122"}, {"id":"689","hider":"M145","seeker":"S122"}, {"id":"690","hider":"R185","seeker":"S122"}, {"id":"691","hider":"J263","seeker":"S122"}, {"id":"692","hider":"R069","seeker":"S122"}, {"id":"693","hider":"M0D7","seeker":"P005"}, {"id":"694","hider":"H1CF","seeker":"P005"}, {"id":"695","hider":"C1CB","seeker":"P005"}, {"id":"696","hider":"R069","seeker":"P005"}, {"id":"697","hider":"R185","seeker":"P005"}, {"id":"698","hider":"J263","seeker":"P005"}, {"id":"699","hider":"A27D","seeker":"P005"}, {"id":"700","hider":"D3B5","seeker":"M3C0"}, {"id":"701","hider":"A193","seeker":"M3C0"}, {"id":"702","hider":"Z1C3","seeker":"M3C0"}, {"id":"703","hider":"W195","seeker":"M3C0"}, {"id":"704","hider":"W08F","seeker":"M3C0"}, {"id":"705","hider":"F3D7","seeker":"M3C0"}, {"id":"706","hider":"R223","seeker":"M3C0"}, {"id":"707","hider":"K3B1","seeker":"M3C0"}, {"id":"708","hider":"I02B","seeker":"M3C0"}, {"id":"709","hider":"M415","seeker":"M332"}, {"id":"710","hider":"R069","seeker":"M332"}, {"id":"711","hider":"J263","seeker":"M332"}, {"id":"712","hider":"R185","seeker":"M332"}, {"id":"713","hider":"S183","seeker":"M332"}, {"id":"714","hider":"N2BB","seeker":"M332"}, {"id":"715","hider":"D2D7","seeker":"M332"}, {"id":"716","hider":"D3B5","seeker":"M332"}, {"id":"717","hider":"J341","seeker":"M3C0"}, {"id":"718","hider":"K107","seeker":"M3C0"}, {"id":"719","hider":"W343","seeker":"M3C0"}, {"id":"720","hider":"A2C5","seeker":"M3C0"}, {"id":"721","hider":"Z1AB","seeker":"M3C0"}, {"id":"722","hider":"D3CB","seeker":"M3C0"}, {"id":"723","hider":"A1D7","seeker":"M3C0"}, {"id":"724","hider":"W205","seeker":"M3C0"}, {"id":"725","hider":"A07B","seeker":"M3C0"}, {"id":"726","hider":"M3C1","seeker":"M3C0"}, {"id":"727","hider":"M3C2","seeker":"M3C0"}, {"id":"728","hider":"E0F9","seeker":"M3C0"}, {"id":"729","hider":"M0E3","seeker":"M3C0"}, {"id":"730","hider":"M12A","seeker":"I02B"}, {"id":"731","hider":"Y41C","seeker":"I02B"}, {"id":"732","hider":"N41D","seeker":"I02B"}, {"id":"733","hider":"J210","seeker":"I02B"}, {"id":"734","hider":"M3C0","seeker":"M3C1"}, {"id":"735","hider":"A1E6","seeker":"M3C1"}, {"id":"736","hider":"A376","seeker":"M3C1"}, {"id":"737","hider":"S1D8","seeker":"M3C1"}, {"id":"738","hider":"S22A","seeker":"M3C1"}, {"id":"739","hider":"S1D8","seeker":"Z18D"}, {"id":"740","hider":"D1F2","seeker":"Z18D"}, {"id":"741","hider":"A30A","seeker":"Z18D"}, {"id":"742","hider":"N354","seeker":"Z18D"}, {"id":"743","hider":"D1F2","seeker":"M3C1"}, {"id":"744","hider":"C29A","seeker":"M3C1"}, {"id":"745","hider":"M256","seeker":"Z1AB"}, {"id":"746","hider":"V255","seeker":"Z1AB"}, {"id":"747","hider":"C27C","seeker":"Z1AB"}, {"id":"748","hider":"H3D4","seeker":"Z1AB"}, {"id":"749","hider":"D110","seeker":"Z1AB"}, {"id":"750","hider":"M2A2","seeker":"M3C1"}, {"id":"751","hider":"B030","seeker":"Z18D"}, {"id":"752","hider":"B402","seeker":"G331"}, {"id":"753","hider":"J210","seeker":"G331"}, {"id":"754","hider":"R223","seeker":"S0C0"}, {"id":"755","hider":"H2DB","seeker":"S0C0"}, {"id":"756","hider":"C0E1","seeker":"S0C0"}, {"id":"757","hider":"Z18D","seeker":"S0C0"}, {"id":"758","hider":"A3E7","seeker":"S0C0"}, {"id":"759","hider":"C3EB","seeker":"S0C0"}, {"id":"760","hider":"J07F","seeker":"S0C0"}, {"id":"761","hider":"I3A8","seeker":"M3C1"}, {"id":"762","hider":"A30A","seeker":"C21B"}, {"id":"763","hider":"S1D8","seeker":"C21B"}, {"id":"764","hider":"D1F2","seeker":"C21B"}, {"id":"765","hider":"C29A","seeker":"C21B"}, {"id":"766","hider":"N354","seeker":"C21B"}, {"id":"767","hider":"B030","seeker":"C21B"}, {"id":"768","hider":"P3D0","seeker":"C21B"}, {"id":"769","hider":"C08A","seeker":"C21B"}, {"id":"770","hider":"A1DC","seeker":"C21B"}, {"id":"771","hider":"H374","seeker":"C21B"}, {"id":"772","hider":"D110","seeker":"C21B"}, {"id":"773","hider":"S22A","seeker":"C21B"}, {"id":"774","hider":"I3A8","seeker":"C21B"}, {"id":"775","hider":"M2A2","seeker":"C21B"}, {"id":"776","hider":"A2BE","seeker":"C21B"}, {"id":"777","hider":"M2B0","seeker":"C21B"}, {"id":"778","hider":"S2AC","seeker":"C21B"}, {"id":"779","hider":"M3A6","seeker":"C21B"}, {"id":"780","hider":"P005","seeker":"C21B"}, {"id":"781","hider":"G0BE","seeker":"C21B"}, {"id":"782","hider":"S3D2","seeker":"Z18D"}, {"id":"783","hider":"K170","seeker":"Z18D"}, {"id":"784","hider":"L0C8","seeker":"Z18D"}, {"id":"785","hider":"L0C8","seeker":"D3B5"}, {"id":"786","hider":"M3C0","seeker":"D3B5"}, {"id":"787","hider":"A376","seeker":"D3B5"}, {"id":"788","hider":"S1D8","seeker":"D3B5"}, {"id":"789","hider":"C29A","seeker":"D3B5"}, {"id":"790","hider":"C1CD","seeker":"B402"}, {"id":"791","hider":"G331","seeker":"B402"}, {"id":"792","hider":"L40D","seeker":"B402"}, {"id":"793","hider":"R069","seeker":"B402"}, {"id":"794","hider":"E3F5","seeker":"B402"}, {"id":"795","hider":"D1F2","seeker":"J24C"}, {"id":"796","hider":"A30A","seeker":"J24C"}, {"id":"797","hider":"S1D8","seeker":"J24C"}, {"id":"798","hider":"N354","seeker":"J24C"}, {"id":"799","hider":"B030","seeker":"J24C"}, {"id":"800","hider":"S3D2","seeker":"J24C"}, {"id":"801","hider":"K170","seeker":"J24C"}, {"id":"802","hider":"L0C8","seeker":"J24C"}, {"id":"803","hider":"C1CD","seeker":"S404"}, {"id":"804","hider":"G331","seeker":"S404"}, {"id":"805","hider":"L40D","seeker":"S404"}, {"id":"806","hider":"R069","seeker":"S404"}, {"id":"807","hider":"E3F5","seeker":"S404"}, {"id":"808","hider":"T32D","seeker":"M2A2"}, {"id":"809","hider":"H0AB","seeker":"M2A2"}, {"id":"810","hider":"E2E1","seeker":"M2A2"}, {"id":"811","hider":"R069","seeker":"M2A2"}, {"id":"812","hider":"S1A3","seeker":"M2A2"}, {"id":"813","hider":"J263","seeker":"M2A2"}, {"id":"814","hider":"R185","seeker":"M2A2"}, {"id":"815","hider":"M415","seeker":"M2A2"}, {"id":"816","hider":"F21F","seeker":"M2A2"}, {"id":"817","hider":"Y334","seeker":"G331"}, {"id":"818","hider":"E321","seeker":"N41D"}, {"id":"819","hider":"M10B","seeker":"N41D"}, {"id":"820","hider":"C22D","seeker":"N41D"}, {"id":"821","hider":"A3A5","seeker":"N41D"}, {"id":"822","hider":"P3A7","seeker":"N41D"}, {"id":"823","hider":"P3A7","seeker":"Y41C"}, {"id":"824","hider":"A3A5","seeker":"Y41C"}, {"id":"825","hider":"C22D","seeker":"Y41C"}, {"id":"826","hider":"M10B","seeker":"Y41C"}, {"id":"827","hider":"F1D1","seeker":"Y41C"}, {"id":"828","hider":"M2D6","seeker":"A2D5"}, {"id":"829","hider":"S2F4","seeker":"A2D5"}, {"id":"830","hider":"R3CA","seeker":"A2D5"}, {"id":"831","hider":"C3C6","seeker":"A2D5"}, {"id":"832","hider":"K3C8","seeker":"A2D5"}, {"id":"833","hider":"S3E2","seeker":"A2D5"}, {"id":"834","hider":"M3C0","seeker":"A2D5"}, {"id":"835","hider":"V410","seeker":"A2D5"}, {"id":"836","hider":"C3EB","seeker":"M2D6"}, {"id":"837","hider":"A3E7","seeker":"M2D6"}, {"id":"838","hider":"J24C","seeker":"M2D6"}, {"id":"839","hider":"A2D5","seeker":"M2D6"}, {"id":"840","hider":"A07B","seeker":"M2D6"}, {"id":"841","hider":"M24F","seeker":"M2D6"}, {"id":"842","hider":"W205","seeker":"M2D6"}, {"id":"843","hider":"A047","seeker":"M2D6"}, {"id":"844","hider":"M35E","seeker":"M35C"}, {"id":"845","hider":"M10B","seeker":"M35C"}, {"id":"846","hider":"C22D","seeker":"M35C"}, {"id":"847","hider":"F1D1","seeker":"M35C"}, {"id":"848","hider":"T0AF","seeker":"M35C"}, {"id":"849","hider":"I335","seeker":"M35C"}, {"id":"850","hider":"E321","seeker":"M35C"}, {"id":"851","hider":"M0D7","seeker":"A3CC"}, {"id":"852","hider":"J263","seeker":"A3CC"}, {"id":"853","hider":"R185","seeker":"A3CC"}, {"id":"854","hider":"N2BB","seeker":"A3CC"}, {"id":"855","hider":"L2BC","seeker":"A3CC"}, {"id":"856","hider":"S1A3","seeker":"A3CC"}, {"id":"857","hider":"E2D9","seeker":"A3CC"}, {"id":"858","hider":"A313","seeker":"A3CC"}, {"id":"859","hider":"M315","seeker":"A3CC"}, {"id":"860","hider":"R10F","seeker":"A3CC"}, {"id":"861","hider":"C3C6","seeker":"A3E7"}, {"id":"862","hider":"R25C","seeker":"A3E7"}, {"id":"863","hider":"S3E2","seeker":"A3E7"}, {"id":"864","hider":"R3CA","seeker":"A3E7"}, {"id":"865","hider":"M24F","seeker":"D1F2"}, {"id":"866","hider":"S183","seeker":"D1F2"}, {"id":"867","hider":"M0D7","seeker":"D1F2"}, {"id":"868","hider":"C21B","seeker":"D1F2"}, {"id":"869","hider":"J405","seeker":"D1F2"}, {"id":"870","hider":"R223","seeker":"A3CC"}, {"id":"871","hider":"M12A","seeker":"J13B"}, {"id":"872","hider":"J210","seeker":"J13B"}, {"id":"873","hider":"G290","seeker":"J13B"}, {"id":"874","hider":"L07E","seeker":"J13B"}, {"id":"875","hider":"M3C0","seeker":"P403"}, {"id":"876","hider":"S3DC","seeker":"P403"}, {"id":"877","hider":"K346","seeker":"P403"}, {"id":"878","hider":"N41D","seeker":"P403"}, {"id":"879","hider":"S268","seeker":"P403"}, {"id":"880","hider":"A048","seeker":"P403"}, {"id":"881","hider":"C21B","seeker":"P3D0"}, {"id":"882","hider":"A191","seeker":"P3D0"}, {"id":"883","hider":"D363","seeker":"P3D0"}, {"id":"884","hider":"M031","seeker":"P3D0"}, {"id":"885","hider":"N2C3","seeker":"P3D0"}, {"id":"886","hider":"L40D","seeker":"P3D0"}, {"id":"887","hider":"R185","seeker":"P3D0"}, {"id":"888","hider":"R069","seeker":"P3D0"}, {"id":"889","hider":"T32D","seeker":"M256"}, {"id":"890","hider":"A32A","seeker":"M256"}, {"id":"891","hider":"C21B","seeker":"M256"}, {"id":"892","hider":"R069","seeker":"M256"}, {"id":"893","hider":"L40D","seeker":"M256"}, {"id":"894","hider":"A3A5","seeker":"M256"}, {"id":"895","hider":"P3A7","seeker":"M256"}, {"id":"896","hider":"T0AF","seeker":"M152"}, {"id":"897","hider":"E321","seeker":"M152"}, {"id":"898","hider":"I335","seeker":"M152"}, {"id":"899","hider":"F1D1","seeker":"M152"}, {"id":"900","hider":"C22D","seeker":"M152"}, {"id":"901","hider":"M0E3","seeker":"M2C6"}, {"id":"902","hider":"W213","seeker":"M2C6"}, {"id":"903","hider":"S22A","seeker":"W205"}, {"id":"904","hider":"A1E6","seeker":"W205"}, {"id":"905","hider":"A376","seeker":"W205"}, {"id":"906","hider":"S1D8","seeker":"W205"}, {"id":"907","hider":"D1F2","seeker":"W205"}, {"id":"908","hider":"C29A","seeker":"W205"}, {"id":"909","hider":"M2A2","seeker":"W205"}, {"id":"910","hider":"M0D7","seeker":"A1E6"}, {"id":"911","hider":"R069","seeker":"A1E6"}, {"id":"912","hider":"J263","seeker":"A1E6"}, {"id":"913","hider":"R185","seeker":"A1E6"}, {"id":"914","hider":"A3A5","seeker":"A1E6"}, {"id":"915","hider":"P3A7","seeker":"A1E6"}, {"id":"916","hider":"R25C","seeker":"C3EB"}, {"id":"917","hider":"C3C6","seeker":"C3EB"}, {"id":"918","hider":"S3E2","seeker":"C3EB"}, {"id":"919","hider":"R3CA","seeker":"C3EB"}, {"id":"920","hider":"I3A8","seeker":"F21F"}, {"id":"921","hider":"R1E0","seeker":"F21F"}, {"id":"922","hider":"M152","seeker":"F21F"}, {"id":"923","hider":"M2C6","seeker":"F21F"}, {"id":"924","hider":"B030","seeker":"F21F"}, {"id":"925","hider":"D110","seeker":"E0F9"}, {"id":"926","hider":"H374","seeker":"F3D7"}, {"id":"927","hider":"D110","seeker":"F3D7"}, {"id":"928","hider":"B030","seeker":"F3D7"}, {"id":"929","hider":"S3D2","seeker":"F3D7"}, {"id":"930","hider":"B21E","seeker":"F3D7"}, {"id":"931","hider":"A048","seeker":"F3D7"}, {"id":"932","hider":"H374","seeker":"E0F9"}, {"id":"933","hider":"M3A6","seeker":"E0F9"}, {"id":"934","hider":"M2B0","seeker":"E0F9"}, {"id":"935","hider":"S2AC","seeker":"E0F9"}, {"id":"936","hider":"A2BE","seeker":"E0F9"}, {"id":"937","hider":"I3A8","seeker":"E0F9"}, {"id":"938","hider":"M2A2","seeker":"E0F9"}, {"id":"939","hider":"C08A","seeker":"E0F9"}, {"id":"940","hider":"B21E","seeker":"E0F9"}, {"id":"941","hider":"B030","seeker":"E0F9"}, {"id":"942","hider":"A30A","seeker":"E0F9"}, {"id":"943","hider":"M256","seeker":"E0F9"}, {"id":"944","hider":"V255","seeker":"E0F9"}, {"id":"945","hider":"P005","seeker":"E0F9"}, {"id":"946","hider":"G0BE","seeker":"E0F9"}, {"id":"947","hider":"A191","seeker":"G0BE"}, {"id":"948","hider":"M0D7","seeker":"G0BE"}, {"id":"949","hider":"R069","seeker":"G0BE"}, {"id":"950","hider":"D363","seeker":"G0BE"}, {"id":"951","hider":"C1CB","seeker":"G0BE"}, {"id":"952","hider":"S3A3","seeker":"G0BE"}, {"id":"953","hider":"H1CF","seeker":"G0BE"}, {"id":"954","hider":"E3F5","seeker":"G0BE"}, {"id":"955","hider":"M24F","seeker":"G0BE"}, {"id":"956","hider":"L40D","seeker":"G0BE"}, {"id":"957","hider":"N2BB","seeker":"G0BE"}, {"id":"958","hider":"D2D7","seeker":"G0BE"}, {"id":"959","hider":"L2BC","seeker":"G0BE"}, {"id":"960","hider":"P005","seeker":"S183"}, {"id":"961","hider":"G0BE","seeker":"S183"}, {"id":"962","hider":"A30A","seeker":"S183"}, {"id":"963","hider":"S1D8","seeker":"S183"}, {"id":"964","hider":"C29A","seeker":"S183"}, {"id":"965","hider":"T230","seeker":"T401"}, {"id":"966","hider":"L0C8","seeker":"T401"}, {"id":"967","hider":"J1D2","seeker":"A1D7"}, {"id":"968","hider":"Y41C","seeker":"M24F"}, {"id":"969","hider":"N41D","seeker":"M24F"}, {"id":"970","hider":"H374","seeker":"Z1AB"}, {"id":"971","hider":"V255","seeker":"W343"}, {"id":"972","hider":"H3D4","seeker":"W343"}, {"id":"973","hider":"C27C","seeker":"W343"}, {"id":"974","hider":"H374","seeker":"W343"}, {"id":"975","hider":"D110","seeker":"W343"}, {"id":"976","hider":"P005","seeker":"W343"}, {"id":"977","hider":"B030","seeker":"W343"}, {"id":"978","hider":"S268","seeker":"T3DF"}, {"id":"979","hider":"H262","seeker":"T3DF"}, {"id":"980","hider":"T11C","seeker":"T3DF"}, {"id":"981","hider":"K10A","seeker":"T3DF"}, {"id":"982","hider":"H1CF","seeker":"P3B2"}, {"id":"983","hider":"C1CB","seeker":"P3B2"}, {"id":"984","hider":"M0E3","seeker":"P3B2"}, {"id":"985","hider":"W08F","seeker":"P3B2"}, {"id":"986","hider":"E0F9","seeker":"P3B2"}, {"id":"987","hider":"K107","seeker":"P3B2"}, {"id":"988","hider":"J341","seeker":"P3B2"}, {"id":"989","hider":"I02B","seeker":"P3B2"}, {"id":"990","hider":"J0E5","seeker":"P3B2"}, {"id":"991","hider":"P403","seeker":"P3B2"}, {"id":"992","hider":"R069","seeker":"P3B2"}, {"id":"993","hider":"J263","seeker":"P3B2"}, {"id":"994","hider":"R185","seeker":"P3B2"}, {"id":"995","hider":"E3F5","seeker":"P3B2"}, {"id":"996","hider":"W213","seeker":"P3B2"}, {"id":"997","hider":"K3B1","seeker":"P3B2"}, {"id":"998","hider":"Z1AB","seeker":"S3D2"}, {"id":"999","hider":"A2C5","seeker":"S3D2"}, {"id":"1000","hider":"W343","seeker":"S3D2"}, {"id":"1001","hider":"J263","seeker":"S3D2"}, {"id":"1002","hider":"R185","seeker":"S3D2"}, {"id":"1003","hider":"M0D7","seeker":"S3D2"}, {"id":"1004","hider":"L40D","seeker":"S3D2"}, {"id":"1005","hider":"A32A","seeker":"S3D2"}, {"id":"1006","hider":"B030","seeker":"R34B"}, {"id":"1007","hider":"C08A","seeker":"R34B"}, {"id":"1008","hider":"T1D0","seeker":"R34B"}, {"id":"1009","hider":"A1DC","seeker":"R34B"}, {"id":"1010","hider":"P005","seeker":"R34B"}, {"id":"1011","hider":"P3D0","seeker":"R34B"}, {"id":"1012","hider":"M332","seeker":"R34B"}, {"id":"1013","hider":"H2A8","seeker":"R34B"}, {"id":"1014","hider":"F32E","seeker":"R34B"}, {"id":"1015","hider":"M12A","seeker":"R34B"}, {"id":"1016","hider":"J210","seeker":"R34B"}, {"id":"1017","hider":"I3A8","seeker":"R34B"}, {"id":"1018","hider":"J263","seeker":"R34B"}, {"id":"1019","hider":"S122","seeker":"R34B"}, {"id":"1020","hider":"M3A6","seeker":"R069"}, {"id":"1021","hider":"H374","seeker":"R069"}, {"id":"1022","hider":"B030","seeker":"R069"}, {"id":"1023","hider":"A048","seeker":"R069"}, {"id":"1024","hider":"M3C0","seeker":"R069"}, {"id":"1025","hider":"H2DB","seeker":"N354"}, {"id":"1026","hider":"F21F","seeker":"N354"}, {"id":"1027","hider":"C0E1","seeker":"N354"}, {"id":"1028","hider":"A2D5","seeker":"N354"}, {"id":"1029","hider":"A3E7","seeker":"N354"}, {"id":"1030","hider":"C3EB","seeker":"N354"}, {"id":"1031","hider":"J24C","seeker":"N354"}, {"id":"1032","hider":"S29B","seeker":"N354"}, {"id":"1033","hider":"M031","seeker":"J3B0"}, {"id":"1034","hider":"N2C3","seeker":"J3B0"}, {"id":"1035","hider":"A32A","seeker":"J3B0"}, {"id":"1036","hider":"B030","seeker":"M0E3"}, {"id":"1037","hider":"D110","seeker":"M0E3"}, {"id":"1038","hider":"H374","seeker":"M0E3"}, {"id":"1039","hider":"R304","seeker":"M0E3"}, {"id":"1040","hider":"W2FC","seeker":"M0E3"}, {"id":"1041","hider":"C08A","seeker":"M0E3"}, {"id":"1042","hider":"M2A2","seeker":"M0E3"}, {"id":"1043","hider":"I3A8","seeker":"M0E3"}, {"id":"1044","hider":"A30A","seeker":"M0E3"}, {"id":"1045","hider":"S3D2","seeker":"M0E3"}, {"id":"1046","hider":"V410","seeker":"M0E3"}, {"id":"1047","hider":"A376","seeker":"M0E3"}, {"id":"1048","hider":"B21E","seeker":"M0E3"}, {"id":"1049","hider":"A2C5","seeker":"M31C"}, {"id":"1050","hider":"M349","seeker":"M31C"}, {"id":"1051","hider":"R34B","seeker":"M31C"}, {"id":"1052","hider":"F1DB","seeker":"M31C"}, {"id":"1053","hider":"K41F","seeker":"M31C"}, {"id":"1054","hider":"B3DB","seeker":"M31C"}, {"id":"1055","hider":"W34D","seeker":"M31C"}, {"id":"1056","hider":"A27D","seeker":"M31C"}, {"id":"1057","hider":"C1CD","seeker":"M31C"}, {"id":"1058","hider":"G331","seeker":"M31C"}, {"id":"1059","hider":"C21B","seeker":"M31C"}, {"id":"1060","hider":"E3F5","seeker":"M31C"}, {"id":"1061","hider":"D3CB","seeker":"M31C"}, {"id":"1062","hider":"A1D7","seeker":"M31C"}, {"id":"1063","hider":"F21F","seeker":"M31C"}, {"id":"1064","hider":"A04F","seeker":"M31C"}, {"id":"1065","hider":"M24F","seeker":"M31C"}, {"id":"1066","hider":"M031","seeker":"S24A"}, {"id":"1067","hider":"M349","seeker":"S24A"}, {"id":"1068","hider":"N2C3","seeker":"S24A"}, {"id":"1069","hider":"R34B","seeker":"S24A"}, {"id":"1070","hider":"C0E1","seeker":"S24A"}, {"id":"1071","hider":"M35F","seeker":"S24A"}, {"id":"1072","hider":"S29B","seeker":"S24A"}, {"id":"1073","hider":"W2DF","seeker":"S24A"}, {"id":"1074","hider":"M3C1","seeker":"S24A"}, {"id":"1075","hider":"J1D9","seeker":"S24A"}, {"id":"1076","hider":"F1DB","seeker":"S24A"}, {"id":"1077","hider":"K41F","seeker":"S24A"}, {"id":"1078","hider":"S268","seeker":"X3B7"}, {"id":"1079","hider":"H262","seeker":"X3B7"}, {"id":"1080","hider":"M31C","seeker":"X3B7"}, {"id":"1081","hider":"M2CA","seeker":"X3B7"}, {"id":"1082","hider":"P2BF","seeker":"X3B7"}, {"id":"1083","hider":"S3DC","seeker":"X3B7"}, {"id":"1084","hider":"K346","seeker":"X3B7"}, {"id":"1085","hider":"N41D","seeker":"X3B7"}, {"id":"1086","hider":"Y41C","seeker":"X3B7"}, {"id":"1087","hider":"M12A","seeker":"X3B7"}, {"id":"1088","hider":"F1D1","seeker":"N41D"}, {"id":"1089","hider":"J0E5","seeker":"K20E"}, {"id":"1090","hider":"J405","seeker":"K20E"}, {"id":"1091","hider":"M3C1","seeker":"K20E"}, {"id":"1092","hider":"X3B7","seeker":"K20E"}, {"id":"1093","hider":"E2E1","seeker":"K20E"}, {"id":"1094","hider":"W08F","seeker":"K20E"}, {"id":"1095","hider":"F3D7","seeker":"K20E"}, {"id":"1096","hider":"K3B1","seeker":"K20E"}, {"id":"1097","hider":"I02B","seeker":"K20E"}, {"id":"1098","hider":"P2BF","seeker":"O1BB"}, {"id":"1099","hider":"M2CA","seeker":"O1BB"}, {"id":"1100","hider":"A2C4","seeker":"O1BB"}, {"id":"1101","hider":"M31C","seeker":"O1BB"}, {"id":"1102","hider":"M080","seeker":"O1BB"}, {"id":"1103","hider":"V410","seeker":"O1BB"}, {"id":"1104","hider":"A02A","seeker":"O1BB"}, {"id":"1105","hider":"Z1AB","seeker":"B15E"}, {"id":"1106","hider":"A2C5","seeker":"B15E"}, {"id":"1107","hider":"W343","seeker":"B15E"}, {"id":"1108","hider":"F3D7","seeker":"B15E"}, {"id":"1109","hider":"R223","seeker":"B15E"}, {"id":"1110","hider":"H3B4","seeker":"E30B"}, {"id":"1111","hider":"P005","seeker":"E30B"}, {"id":"1112","hider":"A30A","seeker":"E30B"}, {"id":"1113","hider":"W2F2","seeker":"E30B"}, {"id":"1114","hider":"A074","seeker":"E30B"}, {"id":"1115","hider":"R304","seeker":"E30B"}, {"id":"1116","hider":"N354","seeker":"E30B"}, {"id":"1117","hider":"P2D4","seeker":"E30B"}, {"id":"1118","hider":"S1D8","seeker":"E30B"}, {"id":"1119","hider":"A376","seeker":"E30B"}, {"id":"1120","hider":"B030","seeker":"M349"}, {"id":"1121","hider":"A1DC","seeker":"M349"}, {"id":"1122","hider":"T1D0","seeker":"M349"}, {"id":"1123","hider":"I3A8","seeker":"M349"}, {"id":"1124","hider":"P005","seeker":"M349"}, {"id":"1125","hider":"P3D0","seeker":"M349"}, {"id":"1126","hider":"A376","seeker":"M349"}, {"id":"1127","hider":"H2A8","seeker":"M349"}, {"id":"1128","hider":"M332","seeker":"M349"}, {"id":"1129","hider":"F3A1","seeker":"M349"}, {"id":"1130","hider":"M12A","seeker":"M349"}, {"id":"1131","hider":"A2A0","seeker":"M349"}, {"id":"1132","hider":"J210","seeker":"M349"}, {"id":"1133","hider":"E2E4","seeker":"J0E5"}, {"id":"1134","hider":"M152","seeker":"J0E5"}, {"id":"1135","hider":"R1E0","seeker":"J0E5"}, {"id":"1136","hider":"B030","seeker":"J0E5"}, {"id":"1137","hider":"N28B","seeker":"A2BE"}, {"id":"1138","hider":"S3A3","seeker":"A2BE"}, {"id":"1139","hider":"C21B","seeker":"A2BE"}, {"id":"1140","hider":"P403","seeker":"A2BE"}, {"id":"1141","hider":"X3B7","seeker":"A2BE"}, {"id":"1142","hider":"M145","seeker":"A2BE"}, {"id":"1143","hider":"L40D","seeker":"A2BE"}, {"id":"1144","hider":"M415","seeker":"A2BE"}, {"id":"1145","hider":"R223","seeker":"A2BE"}, {"id":"1146","hider":"A04F","seeker":"A2BE"}, {"id":"1147","hider":"M24F","seeker":"A2BE"}, {"id":"1148","hider":"R069","seeker":"H212"}, {"id":"1149","hider":"P403","seeker":"H212"}, {"id":"1150","hider":"J263","seeker":"H212"}, {"id":"1151","hider":"R185","seeker":"H212"}, {"id":"1152","hider":"T32D","seeker":"H212"}, {"id":"1153","hider":"S183","seeker":"H212"}, {"id":"1154","hider":"J0E5","seeker":"H212"}, {"id":"1155","hider":"H374","seeker":"E2E1"}, {"id":"1156","hider":"D110","seeker":"E2E1"}, {"id":"1157","hider":"K0E2","seeker":"E2E1"}, {"id":"1158","hider":"D1F2","seeker":"E2E1"}, {"id":"1159","hider":"S1D8","seeker":"E2E1"}, {"id":"1160","hider":"A376","seeker":"E2E1"}, {"id":"1161","hider":"P3D0","seeker":"E2E1"}, {"id":"1162","hider":"P005","seeker":"E2E1"}, {"id":"1163","hider":"C29A","seeker":"E2E1"}, {"id":"1164","hider":"A074","seeker":"E2E1"}, {"id":"1165","hider":"T1D0","seeker":"E2E1"}, {"id":"1166","hider":"A1DC","seeker":"E2E1"}, {"id":"1167","hider":"C08A","seeker":"E2E1"}, {"id":"1168","hider":"B030","seeker":"E2E1"}, {"id":"1169","hider":"P2D4","seeker":"E2E1"}]